th2_data_services_utils/__init__.py
th2_data_services_utils/utils.py
th2_data_services_utils-0.3.5.dev2797484311.dist-info/LICENSE
th2_data_services_utils-0.3.5.dev2797484311.dist-info/METADATA
th2_data_services_utils-0.3.5.dev2797484311.dist-info/WHEEL
th2_data_services_utils-0.3.5.dev2797484311.dist-info/top_level.txt
th2_data_services_utils-0.3.5.dev2797484311.dist-info/RECORD
