Metadata-Version: 2.1
Name: th2-data-services-utils
Version: 0.3.5.dev2797484311
Summary: th2_data_services_utils
Home-page: https://github.com/th2-net/th2-data-services-utils
Author: TH2-devs
Author-email: th2-devs@exactprosystems.com
License: Apache License 2.0
Platform: UNKNOWN
Requires-Python: >=3.7, <3.10
Requires-Dist: anyio (==3.6.1)
Requires-Dist: aplus (==0.11.0)
Requires-Dist: argon2-cffi (==21.3.0)
Requires-Dist: argon2-cffi-bindings (==21.2.0)
Requires-Dist: astropy (==5.1)
Requires-Dist: asttokens (==2.0.5)
Requires-Dist: attrs (==22.1.0)
Requires-Dist: backcall (==0.2.0)
Requires-Dist: beautifulsoup4 (==4.11.1)
Requires-Dist: blake3 (==0.3.1)
Requires-Dist: bleach (==5.0.1)
Requires-Dist: bqplot (==0.12.33)
Requires-Dist: cachetools (==5.2.0)
Requires-Dist: certifi (==2022.6.15)
Requires-Dist: cffi (==1.15.1)
Requires-Dist: charset-normalizer (==2.1.0)
Requires-Dist: click (==8.1.3)
Requires-Dist: cloudpickle (==2.1.0)
Requires-Dist: commonmark (==0.9.1)
Requires-Dist: cycler (==0.11.0)
Requires-Dist: dask[dataframe] (==2022.7.1)
Requires-Dist: debugpy (==1.6.2)
Requires-Dist: decorator (==5.1.1)
Requires-Dist: defusedxml (==0.7.1)
Requires-Dist: entrypoints (==0.4)
Requires-Dist: executing (==0.9.1)
Requires-Dist: fastapi (==0.79.0)
Requires-Dist: fastjsonschema (==2.16.1)
Requires-Dist: filelock (==3.7.1)
Requires-Dist: fonttools (==4.34.4)
Requires-Dist: frozendict (==2.3.4)
Requires-Dist: fsspec (==2022.7.1)
Requires-Dist: future (==0.18.2)
Requires-Dist: h11 (==0.13.0)
Requires-Dist: h5py (==3.7.0)
Requires-Dist: httptools (==0.4.0)
Requires-Dist: idna (==3.3)
Requires-Dist: importlib-metadata (==4.12.0)
Requires-Dist: importlib-resources (==5.9.0)
Requires-Dist: ipydatawidgets (==4.3.1.post1)
Requires-Dist: ipykernel (==6.15.1)
Requires-Dist: ipyleaflet (==0.17.0)
Requires-Dist: ipympl (==0.9.1)
Requires-Dist: ipython (==8.4.0)
Requires-Dist: ipython-genutils (==0.2.0)
Requires-Dist: ipyvolume (==0.5.2)
Requires-Dist: ipyvue (==1.7.0)
Requires-Dist: ipyvuetify (==1.8.2)
Requires-Dist: ipywebrtc (==0.6.0)
Requires-Dist: ipywidgets (==7.7.1)
Requires-Dist: jedi (==0.18.1)
Requires-Dist: jinja2 (==3.1.2)
Requires-Dist: jsonschema (==4.9.1)
Requires-Dist: jupyter-client (==7.3.4)
Requires-Dist: jupyter-core (==4.11.1)
Requires-Dist: jupyterlab-pygments (==0.2.2)
Requires-Dist: jupyterlab-widgets (==1.1.1)
Requires-Dist: kiwisolver (==1.4.4)
Requires-Dist: llvmlite (==0.39.0)
Requires-Dist: locket (==1.0.0)
Requires-Dist: markupsafe (==2.1.1)
Requires-Dist: matplotlib (==3.5.2)
Requires-Dist: matplotlib-inline (==0.1.3)
Requires-Dist: mistune (==0.8.4)
Requires-Dist: nbclient (==0.6.6)
Requires-Dist: nbconvert (==6.5.0)
Requires-Dist: nbformat (==5.4.0)
Requires-Dist: nest-asyncio (==1.5.5)
Requires-Dist: notebook (==6.4.12)
Requires-Dist: numba (==0.56.0)
Requires-Dist: numpy (==1.22.4)
Requires-Dist: packaging (==21.3)
Requires-Dist: pandas (==1.4.3)
Requires-Dist: pandocfilters (==1.5.0)
Requires-Dist: parso (==0.8.3)
Requires-Dist: partd (==1.2.0)
Requires-Dist: pexpect (==4.8.0)
Requires-Dist: pickleshare (==0.7.5)
Requires-Dist: pillow (==9.2.0)
Requires-Dist: pkgutil-resolve-name (==1.3.10)
Requires-Dist: plotly (==5.9.0)
Requires-Dist: progressbar2 (==4.0.0)
Requires-Dist: prometheus-client (==0.14.1)
Requires-Dist: prompt-toolkit (==3.0.30)
Requires-Dist: psutil (==5.9.1)
Requires-Dist: ptyprocess (==0.7.0)
Requires-Dist: pure-eval (==0.2.2)
Requires-Dist: pyarrow (==9.0.0)
Requires-Dist: pycparser (==2.21)
Requires-Dist: pydantic (==1.9.1)
Requires-Dist: pyerfa (==2.0.0.1)
Requires-Dist: pygments (==2.12.0)
Requires-Dist: pyparsing (==3.0.9)
Requires-Dist: pyrsistent (==0.18.1)
Requires-Dist: python-dateutil (==2.8.2)
Requires-Dist: python-dotenv (==0.20.0)
Requires-Dist: python-utils (==3.3.3)
Requires-Dist: pythreejs (==2.3.0)
Requires-Dist: pytz (==2022.1)
Requires-Dist: pyyaml (==6.0)
Requires-Dist: pyzmq (==23.2.0)
Requires-Dist: requests (==2.28.1)
Requires-Dist: rich (==12.5.1)
Requires-Dist: send2trash (==1.8.0)
Requires-Dist: six (==1.16.0)
Requires-Dist: sniffio (==1.2.0)
Requires-Dist: soupsieve (==2.3.2.post1)
Requires-Dist: stack-data (==0.3.0)
Requires-Dist: starlette (==0.19.1)
Requires-Dist: tabulate (==0.8.10)
Requires-Dist: tenacity (==8.0.1)
Requires-Dist: terminado (==0.15.0)
Requires-Dist: tinycss2 (==1.1.1)
Requires-Dist: toolz (==0.12.0)
Requires-Dist: tornado (==6.2)
Requires-Dist: traitlets (==5.3.0)
Requires-Dist: traittypes (==0.2.1)
Requires-Dist: typing-extensions (==4.3.0)
Requires-Dist: urllib3 (==1.26.11)
Requires-Dist: uvicorn[standard] (==0.18.2)
Requires-Dist: uvloop (==0.16.0)
Requires-Dist: vaex (==4.11.1)
Requires-Dist: vaex-astro (==0.9.1)
Requires-Dist: vaex-core (==4.11.1)
Requires-Dist: vaex-hdf5 (==0.12.3)
Requires-Dist: vaex-jupyter (==0.8.0)
Requires-Dist: vaex-ml (==0.18.0)
Requires-Dist: vaex-server (==0.8.1)
Requires-Dist: vaex-viz (==0.5.2)
Requires-Dist: watchfiles (==0.16.1)
Requires-Dist: wcwidth (==0.2.5)
Requires-Dist: webencodings (==0.5.1)
Requires-Dist: websockets (==10.3)
Requires-Dist: widgetsnbextension (==3.6.1)
Requires-Dist: xarray (==2022.6.0)
Requires-Dist: xyzservices (==2022.6.0)
Requires-Dist: zipp (==3.8.1)
